twitcent/__init__.py
twitcent/twitcent.py
twitcent/__pycache__/__init__.cpython-310.pyc
twitcent/__pycache__/config.cpython-310.pyc
twitcent/__pycache__/twitcent.cpython-310.pyc
twitcent/user_data/__init__.py
twitcent/user_data/config.py
twitcent/user_data/__pycache__/__init__.cpython-310.pyc
twitcent/user_data/__pycache__/config.cpython-310.pyc
twitcent-0.0.2.dist-info/LICENSE
twitcent-0.0.2.dist-info/METADATA
twitcent-0.0.2.dist-info/WHEEL
twitcent-0.0.2.dist-info/top_level.txt
twitcent-0.0.2.dist-info/RECORD
