Metadata-Version: 2.1
Name: twitcent
Version: 0.0.2
Summary: A package for analyzing twitter sentiments based on keyword and number of tweets
Home-page: https://nkrtech.com
Download-URL: https://github.com/moinonin/twitcent/archive/refs/heads/main.zip
Author: Nicolus Rotich
Author-email: nicholas.rotich@gmail.com
License: MIT
Project-URL: Bug Tracker, https://github.com/pypa/twitcent/issues
Platform: any
Classifier: License :: OSI Approved :: MIT License
Requires-Python: >=3.7
License-File: LICENSE
Requires-Dist: setuptools (>=57)
Requires-Dist: wheel
Requires-Dist: tweepy (>=4.0.0)
